ocbc_dbs_statement_parser/__init__.py
ocbc_dbs_statement_parser/cli.py
ocbc_dbs_statement_parser/main.py
ocbc_dbs_statement_parser-0.2.1.dist-info/LICENSE
ocbc_dbs_statement_parser-0.2.1.dist-info/METADATA
ocbc_dbs_statement_parser-0.2.1.dist-info/WHEEL
ocbc_dbs_statement_parser-0.2.1.dist-info/entry_points.txt
ocbc_dbs_statement_parser-0.2.1.dist-info/top_level.txt
ocbc_dbs_statement_parser-0.2.1.dist-info/RECORD
